dynamicfluency/__init__.py
dynamicfluency/aeneas_conversion.py
dynamicfluency/model_data.py
dynamicfluency/pos_tagging.py
dynamicfluency/repetitions.py
dynamicfluency/syntactic_analysis.py
dynamicfluency/word_frequencies.py
dynamicfluency/helpers/__init__.py
dynamicfluency/helpers/conversions.py
dynamicfluency/helpers/database_extensions.py
dynamicfluency/helpers/filepath_extensions.py
dynamicfluency/helpers/textgridtier_extensions.py
dynamicfluency/scripts/add_frequency_dictionary.py
dynamicfluency/scripts/convert_aeneas_to_textgrids.py
dynamicfluency/scripts/download_models.py
dynamicfluency/scripts/get_database_columns.py
dynamicfluency/scripts/make_frequencytagged_girds_from_aligned_grids.py
dynamicfluency/scripts/make_postagged_grids_from_aligned_grids.py
dynamicfluency/scripts/make_repetitionstagged_grids_from_postagged_grids.py
dynamicfluency/scripts/make_syntax_grids_from_postagged_grids.py
dynamicfluency-0.2.0.dist-info/LICENSE
dynamicfluency-0.2.0.dist-info/METADATA
dynamicfluency-0.2.0.dist-info/WHEEL
dynamicfluency-0.2.0.dist-info/top_level.txt
dynamicfluency-0.2.0.dist-info/RECORD
