Metadata-Version: 2.1
Name: dynamicfluency
Version: 0.2.0
Summary: The base python package for DynamicFluency: Monitor and understand the dynamicity of linguistic aspects in (L2) speech.
Author-email: JJWRoeloffs <jelleroeloffs@gmail.com>
Project-URL: Homepage, https://github.com/JJWRoeloffs/bare_python_publish
Project-URL: Bug Tracker, https://github.com/JJWRoeloffs/bare_python_publish/issues
Classifier: Programming Language :: Python :: 3
Classifier: License :: OSI Approved :: GNU Affero General Public License v3
Classifier: Operating System :: OS Independent
Requires-Python: >=3.9
License-File: LICENSE
Requires-Dist: pandas ~=1.5
Requires-Dist: numpy ~=1.23
Requires-Dist: praatio ~=5.1
Requires-Dist: nltk ~=3.7
Requires-Dist: spacy ~=3.5
